GrTiPy/Brans_Dicke_Equations.py
GrTiPy/Brans_Dicke_Equations_ab.py
GrTiPy/Christoffel_All.py
GrTiPy/Christoffel_n_ab.py
GrTiPy/CovariantD.py
GrTiPy/Det.py
GrTiPy/Div.py
GrTiPy/Einstein_Equation.py
GrTiPy/Einstein_Equation_ab.py
GrTiPy/Geodesics.py
GrTiPy/Laplacian_operator.py
GrTiPy/Matric_coef.py
GrTiPy/Ricci_Tensor_All.py
GrTiPy/Ricci_Tensor_ab.py
GrTiPy/Ricci_scalar.py
GrTiPy/Riemann_All.py
GrTiPy/Riemann_nabc.py
GrTiPy/Scalar_Brans_Dicke_field_Equation.py
GrTiPy/Spin_connection.py
GrTiPy/Spin_connection_first.py
GrTiPy/Tr.py
GrTiPy/Wely_Tensor_abcd.py
GrTiPy/__init__.py
GrTiPy/acceleration_vector.py
GrTiPy/expansion_scalar.py
GrTiPy/inverse_metric.py
GrTiPy/projection_tensor.py
GrTiPy/shear_tensor_ab.py
GrTiPy-0.1.0.dist-info/DESCRIPTION.rst
GrTiPy-0.1.0.dist-info/METADATA
GrTiPy-0.1.0.dist-info/RECORD
GrTiPy-0.1.0.dist-info/WHEEL
GrTiPy-0.1.0.dist-info/metadata.json
GrTiPy-0.1.0.dist-info/top_level.txt
